agents_hub/__init__.py
agents_hub/agents/README.md
agents_hub/agents/__init__.py
agents_hub/agents/base.py
agents_hub/agents/base_patch.py
agents_hub/agents/cognitive.py
agents_hub/agents/evolution/__init__.py
agents_hub/agents/evolution/learning_agent.py
agents_hub/agents/specialized/__init__.py
agents_hub/coding/README.md
agents_hub/coding/__init__.py
agents_hub/coding/workforce.py
agents_hub/coding/agents/__init__.py
agents_hub/coding/agents/analyst.py
agents_hub/coding/agents/backend_developer.py
agents_hub/coding/agents/devops_engineer.py
agents_hub/coding/agents/frontend_developer.py
agents_hub/coding/agents/project_manager.py
agents_hub/coding/agents/qa_tester.py
agents_hub/coding/agents/security_engineer.py
agents_hub/cognitive/README.md
agents_hub/cognitive/__init__.py
agents_hub/cognitive/architecture.py
agents_hub/cognitive/learning.py
agents_hub/cognitive/memory.py
agents_hub/cognitive/metacognition.py
agents_hub/cognitive/perception.py
agents_hub/cognitive/response_formatter.py
agents_hub/cognitive/reasoning/__init__.py
agents_hub/cognitive/reasoning/abductive.py
agents_hub/cognitive/reasoning/analogical.py
agents_hub/cognitive/reasoning/base.py
agents_hub/cognitive/reasoning/causal.py
agents_hub/cognitive/reasoning/deductive.py
agents_hub/cognitive/reasoning/inductive.py
agents_hub/cognitive/reasoning/manager.py
agents_hub/config/__init__.py
agents_hub/explainability/__init__.py
agents_hub/knowledge/__init__.py
agents_hub/llm/README.md
agents_hub/llm/__init__.py
agents_hub/llm/base.py
agents_hub/llm/providers/__init__.py
agents_hub/llm/providers/anthropic.py
agents_hub/llm/providers/google.py
agents_hub/llm/providers/ollama.py
agents_hub/llm/providers/openai.py
agents_hub/memory/README.md
agents_hub/memory/__init__.py
agents_hub/memory/base.py
agents_hub/memory/backends/__init__.py
agents_hub/memory/backends/in_memory.py
agents_hub/memory/backends/postgres.py
agents_hub/memory/operations/__init__.py
agents_hub/moderation/README.md
agents_hub-0.1.5.dist-info/licenses/LICENSE
agents_hub-0.1.5.dist-info/METADATA
agents_hub-0.1.5.dist-info/WHEEL
agents_hub-0.1.5.dist-info/top_level.txt
agents_hub-0.1.5.dist-info/RECORD
