Metadata-Version: 2.4
Name: agents-hub
Version: 0.1.5
Summary: Advanced Agent Orchestration Framework
Author-email: Emagine Solutions Technology <info@emaginesolutions.com>
License: MIT
Project-URL: Homepage, https://github.com/emagine-solutions/agents-hub
Project-URL: Bug Tracker, https://github.com/emagine-solutions/agents-hub/issues
Keywords: agents,llm,ai,orchestration,cognitive
Classifier: Programming Language :: Python :: 3
Classifier: License :: OSI Approved :: MIT License
Classifier: Operating System :: OS Independent
Classifier: Development Status :: 3 - Alpha
Classifier: Intended Audience :: Developers
Classifier: Topic :: Scientific/Engineering :: Artificial Intelligence
Requires-Python: >=3.9
License-File: LICENSE
Requires-Dist: pydantic>=2.0.0
Requires-Dist: openai>=1.0.0
Requires-Dist: anthropic>=0.5.0
Requires-Dist: google-generativeai>=0.3.0
Requires-Dist: psycopg2-binary>=2.9.0
Requires-Dist: redis>=4.5.0
Requires-Dist: sqlalchemy>=2.0.0
Requires-Dist: pgvector>=0.2.0
Requires-Dist: numpy>=1.24.0
Requires-Dist: httpx>=0.24.0
Requires-Dist: fuzzywuzzy>=0.18.0
Requires-Dist: python-Levenshtein>=0.21.1
Requires-Dist: beautifulsoup4>=4.9.0
Requires-Dist: requests>=2.25.0
Requires-Dist: lxml>=4.6.0
Requires-Dist: aiohttp>=3.8.0
Requires-Dist: playwright>=1.40.0
Requires-Dist: PyPDF2>=2.0.0
Requires-Dist: python-docx>=0.8.10
Requires-Dist: pdfplumber>=0.5.0
Requires-Dist: tqdm>=4.60.0
Requires-Dist: nltk>=3.6.0
Requires-Dist: langfuse>=2.0.0
Requires-Dist: tavily-python>=0.2.0
Requires-Dist: mcp[cli]>=0.1.0
Requires-Dist: gitpython>=3.1.0
Requires-Dist: pytest>=7.0.0
Requires-Dist: python-dotenv>=1.0.0
Requires-Dist: fastapi>=0.100.0
Requires-Dist: uvicorn>=0.22.0
Requires-Dist: jinja2>=3.1.2
Dynamic: license-file
